{"get":"drivers","parameters":{"id":"33"},"errors":[],"results":1,"response":[{"id":33,"name":"Pascal Wehrlein","abbr":"WEH","image":"https:\/\/media-2.api-sports.io\/formula-1\/drivers\/33.png","nationality":"German","country":{"name":null,"code":"DE"},"birthdate":"1994-10-18","birthplace":null,"number":94,"grands_prix_entered":null,"world_championships":3,"podiums":7,"highest_race_finish":{"position":null,"number":null},"highest_grid_position":null,"career_points":"6","teams":[{"season":2017,"team":{"id":8,"name":"Sauber F1 Team","logo":"https:\/\/media-3.api-sports.io\/formula-1\/teams\/8.png"}},{"season":2016,"team":{"id":16,"name":"Manor Racing","logo":"https:\/\/media-2.api-sports.io\/formula-1\/teams\/16.png"}}]}]}